plt2latex/__init__.py
plt2latex/config.py
plt2latex/figure.py
plt2latex/fontsizes.py
plt2latex/patcher.py
plt2latex/plt2latex.py
plt2latex/plt2latex_pgf.py
plt2latex/rcparams.py
plt2latex/rcsetup.py
plt2latex/renderer.py
plt2latex/units.py
plt2latex/tests/__init__.py
plt2latex/tests/test_examples.py
plt2latex-0.0.12.dist-info/METADATA
plt2latex-0.0.12.dist-info/WHEEL
plt2latex-0.0.12.dist-info/top_level.txt
plt2latex-0.0.12.dist-info/RECORD
