Metadata-Version: 2.4
Name: plt2latex
Version: 0.0.12
Summary: Make the pyplot figure perfect for LaTeX
Author: mihail73351
Author-email: mihail73351@gmail.com
Keywords: python,matplotlib,pyplot,plt,latex
Classifier: Development Status :: 1 - Planning
Classifier: Intended Audience :: Developers
Classifier: Programming Language :: Python :: 3
Classifier: Operating System :: Unix
Classifier: Operating System :: MacOS :: MacOS X
Classifier: Operating System :: Microsoft :: Windows
Requires-Dist: matplotlib
Requires-Dist: numpy
Dynamic: author
Dynamic: author-email
Dynamic: classifier
Dynamic: description
Dynamic: description-content-type
Dynamic: keywords
Dynamic: requires-dist
Dynamic: summary
